ruspeechstress/__init__.py
ruspeechstress/dataset.py
ruspeechstress/sound.py
ruspeechstress/stress_detector.py
ruspeechstress/test.py
ruspeechstress/utils.py
ruspeechstress-0.15.dist-info/METADATA
ruspeechstress-0.15.dist-info/WHEEL
ruspeechstress-0.15.dist-info/top_level.txt
ruspeechstress-0.15.dist-info/RECORD
