Metadata-Version: 2.1
Name: ruspeechstress
Version: 0.15
Summary: package for extending word stress dictionaries based on speech analysis
Home-page: https://github.com/pmashkovtseva/ruspeechstres
Author: Polina Mashkovtseva
Author-email: p.mashkovtseva@gmail.com
License: MIT
Platform: UNKNOWN
